esprit/__init__.py
esprit/app.py
esprit/config.py
esprit/dialogs.py
esprit/main.py
esprit/model.py
esprit-0.2.2.dist-info/METADATA
esprit-0.2.2.dist-info/WHEEL
esprit-0.2.2.dist-info/entry_points.txt
esprit-0.2.2.dist-info/RECORD
