Metadata-Version: 2.4
Name: esprit
Version: 0.2.2
Summary: A minimal terminal-based spreadsheet editor
Project-URL: Documentation, https://github.com/mkaz/esprit
Project-URL: Repository, https://github.com/mkaz/esprit
Project-URL: Issues, https://github.com/mkaz/esprit/issues
Author: Marcus Kazmierczak
License: MIT
Keywords: spreadsheet,terminal
Classifier: Development Status :: 4 - Beta
Classifier: Environment :: Console
Classifier: Intended Audience :: End Users/Desktop
Classifier: Natural Language :: English
Classifier: Operating System :: OS Independent
Classifier: Programming Language :: Python :: 3
Requires-Python: >=3.12
Requires-Dist: rich>=13.0.0
Requires-Dist: textual>=0.41.0
